{"name":"PoshProgressBar","tagline":"A PowerShell ProgressBar in XAML using Material Design in XAML Toolkit from ButchersBoy","body":"### PoshProgressBar\r\nThis is a project intended to make it easy to add beautiful GUI based Progressbars to any PowerShell script or project\r\n\r\n### Installation Methods\r\n1. [Download](https://github.com/Tiberriver256/PoshProgressBar/tree/master/PoshProgressBar) and install the module\r\n2. Install from the PowerShell Gallery with the following code:\r\n\r\n`Install-Module -Name PoshProgressBar`\r\n\r\n### Examples\r\n\r\n","google":"UA-70751453-2","note":"Don't delete this file! It's used internally to help with page regeneration."}